monospace/__init__.py
monospace/__main__.py
monospace/cli/__init__.py
monospace/cli/typeset.py
monospace/cli/util.py
monospace/core/__init__.py
monospace/core/domain/__init__.py
monospace/core/domain/blocks.py
monospace/core/domain/document.py
monospace/core/domain/settings.py
monospace/core/formatting/__init__.py
monospace/core/formatting/ansi.py
monospace/core/formatting/formatter.py
monospace/core/formatting/html.py
monospace/core/formatting/iosevka-plus-bold-italic.t42
monospace/core/formatting/iosevka-plus-bold.t42
monospace/core/formatting/iosevka-plus-italic.t42
monospace/core/formatting/iosevka-plus-regular.t42
monospace/core/formatting/postscript.py
monospace/core/formatting/postscript_template.ps
monospace/core/formatting/reverse_glyphs.ps
monospace/core/formatting/styles.py
monospace/core/layout.py
monospace/core/parse.py
monospace/core/process.py
monospace/core/render.py
monospace/core/rendering/__init__.py
monospace/core/rendering/code.py
monospace/core/rendering/images.py
monospace/core/rendering/paragraph.py
monospace/core/symbols/__init__.py
monospace/core/symbols/characters.py
monospace/core/symbols/lines.py
monospace/util.py
monospace-0.1.10.dist-info/entry_points.txt
monospace-0.1.10.dist-info/WHEEL
monospace-0.1.10.dist-info/METADATA
monospace-0.1.10.dist-info/RECORD
